softmax_one/__init__.py
softmax_one/attention.py
softmax_one/softmax_one.py
softmax_one-0.0.2.dist-info/LICENSE
softmax_one-0.0.2.dist-info/WHEEL
softmax_one-0.0.2.dist-info/METADATA
softmax_one-0.0.2.dist-info/RECORD
